nb_phone_extractor/__init__.py
nb_phone_extractor/command_line.py
nb_phone_extractor/condprob_long.pickle
nb_phone_extractor/prior_long.pickle
nb_phone_extractor/training_data_long.pickle
nb_phone_extractor/vocab_list_long.pickle
nb_phone_extractor-0.0.1.dist-info/LICENSE
nb_phone_extractor-0.0.1.dist-info/METADATA
nb_phone_extractor-0.0.1.dist-info/WHEEL
nb_phone_extractor-0.0.1.dist-info/entry_points.txt
nb_phone_extractor-0.0.1.dist-info/top_level.txt
nb_phone_extractor-0.0.1.dist-info/RECORD
